pvmodule/__init__.py
pvmodule/agro_indicators.py
pvmodule/graph.py
pvmodule/inverter.py
pvmodule/irradiance.py
pvmodule/location.py
pvmodule/module.py
pvmodule/pvgis - Copy.py
pvmodule/pvgis.py
pvmodule/simulation.py
pvmodule/system.py
pvmodule/worldmap.py
pvmodule-0.0.189.dist-info/LICENSE
pvmodule-0.0.189.dist-info/METADATA
pvmodule-0.0.189.dist-info/WHEEL
pvmodule-0.0.189.dist-info/top_level.txt
pvmodule-0.0.189.dist-info/RECORD
