Metadata-Version: 2.1
Name: pvmodule
Version: 0.0.189
Summary: A library used to simulate photovoltaic energy production using PVGIS
Author: Fábio Almeida
Author-email: <fabio-r-almeida@outlook.com>
Keywords: Python,PVGIS,Simulator,Photovoltaic,Solar energy,Solar panels,Solar simulation
Classifier: Development Status :: 1 - Planning
Classifier: Intended Audience :: Developers
Classifier: Programming Language :: Python :: 3
Classifier: Operating System :: Unix
Classifier: Operating System :: MacOS :: MacOS X
Classifier: Operating System :: Microsoft :: Windows
License-File: LICENSE
